[
  {
    "guid": "a4674f14-7409-48dd-8960-5c0deda5a1e6",
    "isActive": true,
    "age": 22,
    "eyeColor": "brown",
    "name": "Glenn Doyle",
    "gender": "male",
    "company": "NETPLODE",
    "email": "glenndoyle@netplode.com"
  },
  {
    "guid": "ec77e0fe-ddeb-48b2-93c6-c249783f964b",
    "isActive": true,
    "age": 20,
    "eyeColor": "green",
    "name": "Cathy Shaffer",
    "gender": "female",
    "company": "PETIGEMS",
    "email": "cathyshaffer@petigems.com"
  },
  {
    "guid": "a2ab7790-f92e-4a45-b069-cf23d97d76b2",
    "isActive": true,
    "age": 40,
    "eyeColor": "green",
    "name": "Miranda Bernard",
    "gender": "female",
    "company": "VERBUS",
    "email": "mirandabernard@verbus.com"
  },
  {
    "guid": "bc2801a5-87f6-4a7c-9285-a3e8d1cfbeec",
    "isActive": true,
    "age": 23,
    "eyeColor": "blue",
    "name": "Lynn Cole",
    "gender": "male",
    "company": "ZIZZLE",
    "email": "lynncole@zizzle.com"
  },
  {
    "guid": "9d6a20c3-a84f-4693-82b7-3a70bc8baa48",
    "isActive": false,
    "age": 36,
    "eyeColor": "green",
    "name": "Hallie Solis",
    "gender": "female",
    "company": "HOPELI",
    "email": "halliesolis@hopeli.com"
  },
  {
    "guid": "fbf1f0b1-9277-4e7f-99af-bc117c518987",
    "isActive": true,
    "age": 37,
    "eyeColor": "blue",
    "name": "Maureen Farmer",
    "gender": "female",
    "company": "TERRAGEN",
    "email": "maureenfarmer@terragen.com"
  },
  {
    "guid": "b54bda68-a405-412d-bd93-d674edff0fb5",
    "isActive": false,
    "age": 21,
    "eyeColor": "brown",
    "name": "Lorena Beasley",
    "gender": "female",
    "company": "GLUKGLUK",
    "email": "lorenabeasley@glukgluk.com"
  },
  {
    "guid": "173560fb-629f-4e7b-9d3a-688b3de4de24",
    "isActive": false,
    "age": 25,
    "eyeColor": "green",
    "name": "Odonnell Morton",
    "gender": "male",
    "company": "FANFARE",
    "email": "odonnellmorton@fanfare.com"
  },
  {
    "guid": "a7f825fa-1ea3-483e-9d59-996277adb08b",
    "isActive": false,
    "age": 20,
    "eyeColor": "green",
    "name": "Good Justice",
    "gender": "male",
    "company": "GEEKMOSIS",
    "email": "goodjustice@geekmosis.com"
  },
  {
    "guid": "935a2fe0-5117-439d-b702-712398df1b95",
    "isActive": true,
    "age": 33,
    "eyeColor": "blue",
    "name": "Boyle Holder",
    "gender": "male",
    "company": "VIAGRAND",
    "email": "boyleholder@viagrand.com"
  },
  {
    "guid": "5b1cbcdb-80c7-417b-9df8-dc59e6f172ea",
    "isActive": true,
    "age": 32,
    "eyeColor": "brown",
    "name": "Diaz Brewer",
    "gender": "male",
    "company": "ZILLACTIC",
    "email": "diazbrewer@zillactic.com"
  },
  {
    "guid": "0ed46b18-44be-4e6a-8a7c-5697e0c40f36",
    "isActive": true,
    "age": 36,
    "eyeColor": "brown",
    "name": "Walton Steele",
    "gender": "male",
    "company": "STEELFAB",
    "email": "waltonsteele@steelfab.com"
  },
  {
    "guid": "1431b353-376e-45a0-925e-2dfb370b6072",
    "isActive": false,
    "age": 21,
    "eyeColor": "blue",
    "name": "Maryanne Herring",
    "gender": "female",
    "company": "MINGA",
    "email": "maryanneherring@minga.com"
  },
  {
    "guid": "22eb222d-57ad-476e-b158-225df8a692bf",
    "isActive": false,
    "age": 26,
    "eyeColor": "blue",
    "name": "Shields Kane",
    "gender": "male",
    "company": "SONGBIRD",
    "email": "shieldskane@songbird.com"
  },
  {
    "guid": "b5a20f4e-a9e0-47f3-879d-bcca1685bad7",
    "isActive": false,
    "age": 34,
    "eyeColor": "blue",
    "name": "Aileen Rhodes",
    "gender": "female",
    "company": "SPORTAN",
    "email": "aileenrhodes@sportan.com"
  },
  {
    "guid": "7a77efcf-1337-4962-998d-115620233003",
    "isActive": true,
    "age": 32,
    "eyeColor": "brown",
    "name": "Shannon Dillard",
    "gender": "male",
    "company": "COMVEYOR",
    "email": "shannondillard@comveyor.com"
  },
  {
    "guid": "e6ce966d-efbe-4b8f-aa9f-13c97478beee",
    "isActive": true,
    "age": 25,
    "eyeColor": "blue",
    "name": "Kenya Koch",
    "gender": "female",
    "company": "QUINEX",
    "email": "kenyakoch@quinex.com"
  },
  {
    "guid": "1ae259f6-3e07-4726-8f53-437ddb3b7988",
    "isActive": false,
    "age": 29,
    "eyeColor": "green",
    "name": "Cindy Whitney",
    "gender": "female",
    "company": "KRAGGLE",
    "email": "cindywhitney@kraggle.com"
  },
  {
    "guid": "5a280e6f-5804-458b-81d5-541750609372",
    "isActive": false,
    "age": 33,
    "eyeColor": "blue",
    "name": "Marci Robbins",
    "gender": "female",
    "company": "GOLISTIC",
    "email": "marcirobbins@golistic.com"
  },
  {
    "guid": "e337861f-9476-41e8-b543-5f498f0ccc1b",
    "isActive": true,
    "age": 36,
    "eyeColor": "brown",
    "name": "Kimberly Schultz",
    "gender": "female",
    "company": "VOLAX",
    "email": "kimberlyschultz@volax.com"
  },
  {
    "guid": "36adafca-9ef0-45bb-b496-7e426d8b564c",
    "isActive": true,
    "age": 39,
    "eyeColor": "blue",
    "name": "Nicholson Mayo",
    "gender": "male",
    "company": "GONKLE",
    "email": "nicholsonmayo@gonkle.com"
  },
  {
    "guid": "d099c9da-a026-418c-bbe4-981e4c1a4eeb",
    "isActive": true,
    "age": 32,
    "eyeColor": "green",
    "name": "Beck Cline",
    "gender": "male",
    "company": "INRT",
    "email": "beckcline@inrt.com"
  },
  {
    "guid": "1ead47ba-f8d3-4dff-b203-39ad3b3bd690",
    "isActive": true,
    "age": 29,
    "eyeColor": "blue",
    "name": "Natalie Vega",
    "gender": "female",
    "company": "SNIPS",
    "email": "natalievega@snips.com"
  },
  {
    "guid": "8df25f86-a375-48f4-9816-943c18b2531f",
    "isActive": false,
    "age": 37,
    "eyeColor": "green",
    "name": "Aisha Black",
    "gender": "female",
    "company": "QUIZKA",
    "email": "aishablack@quizka.com"
  },
  {
    "guid": "caa2be75-1f15-4bda-94c0-d2e4bc9c1555",
    "isActive": true,
    "age": 22,
    "eyeColor": "blue",
    "name": "Odom Swanson",
    "gender": "male",
    "company": "MAGMINA",
    "email": "odomswanson@magmina.com"
  },
  {
    "guid": "cc52dd95-1554-4ca4-bb7b-3b2c9a5beab4",
    "isActive": true,
    "age": 37,
    "eyeColor": "blue",
    "name": "Amparo Lyons",
    "gender": "female",
    "company": "CHORIZON",
    "email": "amparolyons@chorizon.com"
  },
  {
    "guid": "779d95ce-f574-45b6-903c-c34fe72da516",
    "isActive": false,
    "age": 23,
    "eyeColor": "blue",
    "name": "Corina Hampton",
    "gender": "female",
    "company": "FUTURIS",
    "email": "corinahampton@futuris.com"
  },
  {
    "guid": "d1084270-1107-4a49-b223-b5d57bc59f8c",
    "isActive": false,
    "age": 24,
    "eyeColor": "green",
    "name": "Banks Jordan",
    "gender": "male",
    "company": "YOGASM",
    "email": "banksjordan@yogasm.com"
  },
  {
    "guid": "d6d34beb-1840-46e8-898d-8d19bab450a1",
    "isActive": false,
    "age": 39,
    "eyeColor": "green",
    "name": "Dodson Stokes",
    "gender": "male",
    "company": "ACCIDENCY",
    "email": "dodsonstokes@accidency.com"
  },
  {
    "guid": "06ef8680-9f56-455a-ae65-90b8c75d53ed",
    "isActive": true,
    "age": 25,
    "eyeColor": "brown",
    "name": "Olive Mccall",
    "gender": "female",
    "company": "ZILPHUR",
    "email": "olivemccall@zilphur.com"
  },
  {
    "guid": "035415a8-62be-4b66-8b1f-0260b8684271",
    "isActive": false,
    "age": 39,
    "eyeColor": "green",
    "name": "Susan Haley",
    "gender": "female",
    "company": "NURALI",
    "email": "susanhaley@nurali.com"
  },
  {
    "guid": "808cdaf3-f6eb-4c94-8d3d-d79904799282",
    "isActive": true,
    "age": 37,
    "eyeColor": "green",
    "name": "Snyder Castro",
    "gender": "male",
    "company": "ANARCO",
    "email": "snydercastro@anarco.com"
  },
  {
    "guid": "9247d5e4-bb72-4361-be8d-6a591249ee34",
    "isActive": false,
    "age": 39,
    "eyeColor": "green",
    "name": "Le Parker",
    "gender": "male",
    "company": "RODEOCEAN",
    "email": "leparker@rodeocean.com"
  },
  {
    "guid": "5f2146fb-6912-4c61-beef-65b1d3a10224",
    "isActive": false,
    "age": 31,
    "eyeColor": "blue",
    "name": "Luz Rojas",
    "gender": "female",
    "company": "LOCAZONE",
    "email": "luzrojas@locazone.com"
  },
  {
    "guid": "41be9d67-25ce-483d-8e9d-ee3fa91e83d7",
    "isActive": false,
    "age": 37,
    "eyeColor": "blue",
    "name": "Everett Hutchinson",
    "gender": "male",
    "company": "OTHERSIDE",
    "email": "everetthutchinson@otherside.com"
  },
  {
    "guid": "2cc66eb7-2ba9-4514-8a0c-bd8d36852dbe",
    "isActive": true,
    "age": 27,
    "eyeColor": "blue",
    "name": "Logan Waters",
    "gender": "male",
    "company": "OPTICOM",
    "email": "loganwaters@opticom.com"
  },
  {
    "guid": "c6a20e05-62c9-4ee0-a149-a11ae018433d",
    "isActive": false,
    "age": 37,
    "eyeColor": "blue",
    "name": "Bullock Sosa",
    "gender": "male",
    "company": "KEEG",
    "email": "bullocksosa@keeg.com"
  },
  {
    "guid": "0ecce943-064e-4d32-804b-db4b8f8388aa",
    "isActive": true,
    "age": 27,
    "eyeColor": "brown",
    "name": "Robles Bird",
    "gender": "male",
    "company": "CALCULA",
    "email": "roblesbird@calcula.com"
  },
  {
    "guid": "662a4fd4-c366-4a6a-a214-ccc4df6d5db6",
    "isActive": false,
    "age": 35,
    "eyeColor": "blue",
    "name": "Edwards Mack",
    "gender": "male",
    "company": "KINDALOO",
    "email": "edwardsmack@kindaloo.com"
  },
  {
    "guid": "5e399634-2c1c-4e33-9a5b-520123afbcc1",
    "isActive": true,
    "age": 25,
    "eyeColor": "green",
    "name": "Aguilar Wiley",
    "gender": "male",
    "company": "NITRACYR",
    "email": "aguilarwiley@nitracyr.com"
  },
  {
    "guid": "881f91bb-aaf1-452e-8b0b-b52b27365738",
    "isActive": true,
    "age": 23,
    "eyeColor": "brown",
    "name": "Chandler Ramirez",
    "gender": "male",
    "company": "DIGIFAD",
    "email": "chandlerramirez@digifad.com"
  },
  {
    "guid": "6376bd79-9605-4038-a6ae-9c958b16f5b0",
    "isActive": false,
    "age": 29,
    "eyeColor": "green",
    "name": "Tamra Blackburn",
    "gender": "female",
    "company": "PRIMORDIA",
    "email": "tamrablackburn@primordia.com"
  },
  {
    "guid": "f39c90e6-62b6-4682-a1ed-b138e64d3275",
    "isActive": false,
    "age": 37,
    "eyeColor": "blue",
    "name": "Brittany Strickland",
    "gender": "female",
    "company": "XIIX",
    "email": "brittanystrickland@xiix.com"
  },
  {
    "guid": "62f2ef0c-5091-4459-90e4-840b66bb0912",
    "isActive": true,
    "age": 23,
    "eyeColor": "brown",
    "name": "Casandra Jacobs",
    "gender": "female",
    "company": "LETPRO",
    "email": "casandrajacobs@letpro.com"
  },
  {
    "guid": "9a3724b1-cfc3-40c8-9714-e6fc4d501fb8",
    "isActive": false,
    "age": 36,
    "eyeColor": "brown",
    "name": "Luna Gross",
    "gender": "male",
    "company": "VURBO",
    "email": "lunagross@vurbo.com"
  },
  {
    "guid": "de26b629-ab55-4ce3-89f0-cb3bcd3ffe21",
    "isActive": true,
    "age": 31,
    "eyeColor": "blue",
    "name": "Witt Hyde",
    "gender": "male",
    "company": "CUIZINE",
    "email": "witthyde@cuizine.com"
  },
  {
    "guid": "0a7ac726-9a4b-4625-951c-1e5b66478b1b",
    "isActive": true,
    "age": 28,
    "eyeColor": "green",
    "name": "Cameron Hamilton",
    "gender": "male",
    "company": "XINWARE",
    "email": "cameronhamilton@xinware.com"
  },
  {
    "guid": "27900545-b213-4668-99d2-8111fed4736a",
    "isActive": false,
    "age": 25,
    "eyeColor": "blue",
    "name": "Margie Suarez",
    "gender": "female",
    "company": "TALAE",
    "email": "margiesuarez@talae.com"
  },
  {
    "guid": "34115002-a774-405b-99b0-cb6ef2df2778",
    "isActive": true,
    "age": 28,
    "eyeColor": "brown",
    "name": "Cox Gilliam",
    "gender": "male",
    "company": "RONELON",
    "email": "coxgilliam@ronelon.com"
  },
  {
    "guid": "6dc4397f-4600-42b8-a176-7fef6a84901d",
    "isActive": true,
    "age": 37,
    "eyeColor": "green",
    "name": "Williamson Newman",
    "gender": "male",
    "company": "SPACEWAX",
    "email": "williamsonnewman@spacewax.com"
  }
]